MANIFEST.in
README.rst
setup.py
django_twittersync_oauth.egg-info/PKG-INFO
django_twittersync_oauth.egg-info/SOURCES.txt
django_twittersync_oauth.egg-info/dependency_links.txt
django_twittersync_oauth.egg-info/not-zip-safe
django_twittersync_oauth.egg-info/requires.txt
django_twittersync_oauth.egg-info/top_level.txt
twittersync_oauth/__init__.py
twittersync_oauth/helpers.py
twittersync_oauth/models.py
twittersync_oauth/tests.py
twittersync_oauth/views.py
twittersync_oauth/management/__init__.py
twittersync_oauth/management/commands/__init__.py
twittersync_oauth/management/commands/auth_twitter.py
twittersync_oauth/management/commands/sync_twitter_accounts.py