Metadata-Version: 1.0
Name: django-twittersync-oauth
Version: 0.1.1
Summary: OAuth Plugin for django-twittersync
Home-page: http://github.com/vad/django-twittersync-oauth
Author: Davide Setti
Author-email: davide.setti@gmail.com
License: BSD License
Platform: UNKNOWN
Classifier: Framework :: Django
Classifier: Intended Audience :: Developers
Classifier: License :: OSI Approved :: BSD License
Classifier: Operating System :: OS Independent
Classifier: Programming Language :: Python
Classifier: Topic :: Software Development
